azure/mgmt/redhatopenshift/__init__.py
azure/mgmt/redhatopenshift/_azure_red_hat_open_shift_client.py
azure/mgmt/redhatopenshift/_configuration.py
azure/mgmt/redhatopenshift/_patch.py
azure/mgmt/redhatopenshift/_serialization.py
azure/mgmt/redhatopenshift/_version.py
azure/mgmt/redhatopenshift/py.typed
azure/mgmt/redhatopenshift/aio/__init__.py
azure/mgmt/redhatopenshift/aio/_azure_red_hat_open_shift_client.py
azure/mgmt/redhatopenshift/aio/_configuration.py
azure/mgmt/redhatopenshift/aio/_patch.py
azure/mgmt/redhatopenshift/aio/operations/__init__.py
azure/mgmt/redhatopenshift/aio/operations/_machine_pools_operations.py
azure/mgmt/redhatopenshift/aio/operations/_open_shift_clusters_operations.py
azure/mgmt/redhatopenshift/aio/operations/_open_shift_versions_operations.py
azure/mgmt/redhatopenshift/aio/operations/_operations.py
azure/mgmt/redhatopenshift/aio/operations/_patch.py
azure/mgmt/redhatopenshift/aio/operations/_secrets_operations.py
azure/mgmt/redhatopenshift/aio/operations/_sync_identity_providers_operations.py
azure/mgmt/redhatopenshift/aio/operations/_sync_sets_operations.py
azure/mgmt/redhatopenshift/models/__init__.py
azure/mgmt/redhatopenshift/models/_azure_red_hat_open_shift_client_enums.py
azure/mgmt/redhatopenshift/models/_models_py3.py
azure/mgmt/redhatopenshift/models/_patch.py
azure/mgmt/redhatopenshift/operations/__init__.py
azure/mgmt/redhatopenshift/operations/_machine_pools_operations.py
azure/mgmt/redhatopenshift/operations/_open_shift_clusters_operations.py
azure/mgmt/redhatopenshift/operations/_open_shift_versions_operations.py
azure/mgmt/redhatopenshift/operations/_operations.py
azure/mgmt/redhatopenshift/operations/_patch.py
azure/mgmt/redhatopenshift/operations/_secrets_operations.py
azure/mgmt/redhatopenshift/operations/_sync_identity_providers_operations.py
azure/mgmt/redhatopenshift/operations/_sync_sets_operations.py
azure_mgmt_redhatopenshift-2.0.0.dist-info/LICENSE
azure_mgmt_redhatopenshift-2.0.0.dist-info/METADATA
azure_mgmt_redhatopenshift-2.0.0.dist-info/WHEEL
azure_mgmt_redhatopenshift-2.0.0.dist-info/top_level.txt
azure_mgmt_redhatopenshift-2.0.0.dist-info/RECORD
